{
  "actionPools": [
    {
      "actions": [
        {
          "actionId": "actionBehaviour",
          "ax12Id": 1,
          "speed": 255,
          "acceleration": 60,
          "compliance": 1
        },
        {
          "actionId": "actionBehaviour",
          "ax12Id": 3,
          "speed": 255,
          "acceleration": 60,
          "compliance": 1
        }
      ]
    },
    {
      "actions": [
        {
          "actionId": "actionSerialFlag",
          "serialFlagId": "RTS",
          "serialFlagEnabled": false
        },
        {
          "actionId": "actionSerialFlag",
          "serialFlagId": "DTR",
          "serialFlagEnabled": false
        }
      ]
    },
    {
      "actions": [
        {
          "description": "On détent le bras au maximum",
          "actionId": "actionPosition",
          "ax12Id": 1,
          "angleDegrees": 156
        }
      ]
    },
    {
      "actions": [
        {
          "description": "On rentre l'avant bras",
          "actionId": "actionPosition",
          "ax12Id": 3,
          "angleDegrees": 258
        }
      ]
    },
    {
      "actions": [
        {
          "description": "On rentre le bras",
          "actionId": "actionPosition",
          "ax12Id": 1,
          "angleDegrees": 115
        }
      ]
    }
  ]
}